pyncview/__init__.py
pyncview/multiplot.py
pyncview/pyncview.png
pyncview/pyncview.py
pyncview-0.99.42.dist-info/METADATA
pyncview-0.99.42.dist-info/WHEEL
pyncview-0.99.42.dist-info/entry_points.txt
pyncview-0.99.42.dist-info/licenses/LICENSE
pyncview-0.99.42.dist-info/RECORD
