Metadata-Version: 2.4
Name: pyncview
Version: 0.99.42
Summary: NetCDF viewer written in Python
Project-URL: Homepage, https://github.com/BoldingBruggeman/pyncview
Author-email: Jorn Bruggeman <jorn@bolding-bruggeman.com>
License-File: LICENSE
Classifier: Development Status :: 5 - Production/Stable
Classifier: License :: OSI Approved :: GNU General Public License v2 (GPLv2)
Classifier: Operating System :: OS Independent
Classifier: Programming Language :: Python :: 3
Classifier: Topic :: Software Development :: Libraries :: Python Modules
Requires-Python: >=3.8
Requires-Dist: xmlplot>=0.9.32
